{
	"configurations" : 
	[
		{
			"directories" : 
			[
				{
					"build" : ".",
					"childIndexes" : 
					[
						1
					],
					"hasInstallRule" : true,
					"jsonFile" : "directory-.-3cf4975d8f8bfb68b232.json",
					"minimumCMakeVersion" : 
					{
						"string" : "3.12"
					},
					"projectIndex" : 0,
					"source" : ".",
					"targetIndexes" : 
					[
						2,
						3,
						4,
						5,
						6,
						7
					]
				},
				{
					"build" : "gtest",
					"jsonFile" : "directory-gtest-a2408fe1a73b92c5e636.json",
					"minimumCMakeVersion" : 
					{
						"string" : "3.8"
					},
					"parentIndex" : 0,
					"projectIndex" : 1,
					"source" : "/opt/ros/humble/src/gtest_vendor",
					"targetIndexes" : 
					[
						0,
						1
					]
				}
			],
			"name" : "",
			"projects" : 
			[
				{
					"childIndexes" : 
					[
						1
					],
					"directoryIndexes" : 
					[
						0
					],
					"name" : "mocap4r2_vicon_driver",
					"targetIndexes" : 
					[
						2,
						3,
						4,
						5,
						6,
						7
					]
				},
				{
					"directoryIndexes" : 
					[
						1
					],
					"name" : "gtest",
					"parentIndex" : 0,
					"targetIndexes" : 
					[
						0,
						1
					]
				}
			],
			"targets" : 
			[
				{
					"directoryIndex" : 1,
					"id" : "gtest::@0af4add9fe94340e763e",
					"jsonFile" : "target-gtest-878797ce187086ea962c.json",
					"name" : "gtest",
					"projectIndex" : 1
				},
				{
					"directoryIndex" : 1,
					"id" : "gtest_main::@0af4add9fe94340e763e",
					"jsonFile" : "target-gtest_main-3948272c8a86aba99cca.json",
					"name" : "gtest_main",
					"projectIndex" : 1
				},
				{
					"directoryIndex" : 0,
					"id" : "mocap4r2_vicon_driver::@6890427a1f51a3e7e1df",
					"jsonFile" : "target-mocap4r2_vicon_driver-f08595c0fb6a973a96a2.json",
					"name" : "mocap4r2_vicon_driver",
					"projectIndex" : 0
				},
				{
					"directoryIndex" : 0,
					"id" : "mocap4r2_vicon_driver_main::@6890427a1f51a3e7e1df",
					"jsonFile" : "target-mocap4r2_vicon_driver_main-1b87f5ec513ddf3d47bb.json",
					"name" : "mocap4r2_vicon_driver_main",
					"projectIndex" : 0
				},
				{
					"directoryIndex" : 0,
					"id" : "mocap4r2_vicon_driver_uninstall::@6890427a1f51a3e7e1df",
					"jsonFile" : "target-mocap4r2_vicon_driver_uninstall-baf1087ea0f29bd55e45.json",
					"name" : "mocap4r2_vicon_driver_uninstall",
					"projectIndex" : 0
				},
				{
					"directoryIndex" : 0,
					"id" : "test_mocap4r2_vicon_driver::@6890427a1f51a3e7e1df",
					"jsonFile" : "target-test_mocap4r2_vicon_driver-b432472db25d4e6ac967.json",
					"name" : "test_mocap4r2_vicon_driver",
					"projectIndex" : 0
				},
				{
					"directoryIndex" : 0,
					"id" : "uninstall::@6890427a1f51a3e7e1df",
					"jsonFile" : "target-uninstall-cd256b146650fa5a233f.json",
					"name" : "uninstall",
					"projectIndex" : 0
				},
				{
					"directoryIndex" : 0,
					"id" : "vicon_sdk::@6890427a1f51a3e7e1df",
					"jsonFile" : "target-vicon_sdk-ed7f979699e31f9b8d44.json",
					"name" : "vicon_sdk",
					"projectIndex" : 0
				}
			]
		}
	],
	"kind" : "codemodel",
	"paths" : 
	{
		"build" : "/ws/build/mocap4r2_vicon_driver",
		"source" : "/ws/src/mocap4ros2_vicon/mocap4r2_vicon_driver"
	},
	"version" : 
	{
		"major" : 2,
		"minor" : 3
	}
}
